extraexceptions/__init__.py
extraexceptions/cognitivebiases.py
extraexceptions/ignoreexceptions.py
extraexceptions/logicalfallacies.py
extraexceptions-0.0.0.5.dist-info/LICENSE
extraexceptions-0.0.0.5.dist-info/METADATA
extraexceptions-0.0.0.5.dist-info/WHEEL
extraexceptions-0.0.0.5.dist-info/top_level.txt
extraexceptions-0.0.0.5.dist-info/RECORD
