Metadata-Version: 2.1
Name: extraexceptions
Version: 0.0.0.5
Summary: This is a lib for custom exceptions
Home-page: https://github.com/Gerutro/extra_exceptions
Author: Ger
Author-email: gerutrogame@gmail.com
License: MIT License, see LICENCE file
Project-URL: GitHub, https://github.com/Gerutro
Keywords: extra exception lib library
Classifier: Programming Language :: Python :: 3.12
Classifier: License :: OSI Approved :: MIT License
Classifier: Operating System :: OS Independent
Requires-Python: >=3.9
License-File: LICENSE
